LICENSE
README.md
candlefl/__init__.py
candlefl/cli.py
candlefl/compatibility.py
candlefl/config_resolver.py
candlefl/datamodules/__init__.py
candlefl/datamodules/base.py
candlefl/datamodules/cifar.py
candlefl/datamodules/emnist.py
candlefl/datamodules/fashionmnist.py
candlefl/datamodules/types.py
candlefl/federated/__init__.py
candlefl/federated/agents/__init__.py
candlefl/federated/agents/base.py
candlefl/federated/agents/v1.py
candlefl/federated/aggregators/__init__.py
candlefl/federated/aggregators/base.py
candlefl/federated/aggregators/fedavg.py
candlefl/federated/entrypoint.py
candlefl/federated/fl_params.py
candlefl/federated/samplers/__init__.py
candlefl/federated/samplers/base.py
candlefl/federated/samplers/random.py
candlefl/federated/types.py
candlefl/models/__init__.py
candlefl/models/core/__init__.py
candlefl/models/core/cifar/__init__.py
candlefl/models/core/cifar/cifar10/__init__.py
candlefl/models/core/cifar/cifar10/alexnet.py
candlefl/models/core/cifar/cifar10/densenet.py
candlefl/models/core/cifar/cifar10/lenet.py
candlefl/models/core/cifar/cifar10/mobilenet.py
candlefl/models/core/cifar/cifar10/resnet.py
candlefl/models/core/cifar/cifar10/shufflenetv2.py
candlefl/models/core/cifar/cifar10/squeezenet.py
candlefl/models/core/cifar/cifar10/vgg.py
candlefl/models/core/cifar/cifar100/__init__.py
candlefl/models/core/cifar/cifar100/alexnet.py
candlefl/models/core/cifar/cifar100/densenet.py
candlefl/models/core/cifar/cifar100/lenet.py
candlefl/models/core/cifar/cifar100/mobilenet.py
candlefl/models/core/cifar/cifar100/resnet.py
candlefl/models/core/cifar/cifar100/shufflenetv2.py
candlefl/models/core/cifar/cifar100/squeezenet.py
candlefl/models/core/cifar/cifar100/vgg.py
candlefl/models/core/emnist/__init__.py
candlefl/models/core/emnist/balanced/__init__.py
candlefl/models/core/emnist/balanced/alexnet.py
candlefl/models/core/emnist/balanced/densenet.py
candlefl/models/core/emnist/balanced/lenet.py
candlefl/models/core/emnist/balanced/mlp.py
candlefl-0.2.3.dist-info/LICENSE
candlefl-0.2.3.dist-info/METADATA
candlefl-0.2.3.dist-info/WHEEL
candlefl-0.2.3.dist-info/entry_points.txt
candlefl-0.2.3.dist-info/RECORD
