Metadata-Version: 2.1
Name: candlefl
Version: 0.2.3
Summary: A Python library for rapid prototyping, experimenting, and logging of federated learning using state-of-the-art models and datasets. Built using PyTorch and PyTorch Lightning.
Home-page: https://candlefl.readthedocs.io/en/latest/
License: GNU General Public License v3
Keywords: federated-learning,pytorch,pytorch-lightning,candlefl
Author: slothrabbit77 
Author-email: slothrabbit77@gmail.com
Requires-Python: >=3.8,<4.0
Classifier: Development Status :: 4 - Beta
Classifier: Intended Audience :: Developers
Classifier: License :: OSI Approved :: GNU General Public License v3 (GPLv3)
Classifier: License :: Other/Proprietary License
Classifier: Natural Language :: English
Classifier: Programming Language :: Python :: 3
Classifier: Programming Language :: Python :: 3.8
Classifier: Programming Language :: Python :: 3.9
Classifier: Programming Language :: Python :: 3.10
Classifier: Programming Language :: Python :: 3.11
Classifier: Programming Language :: Python :: 3.12
Requires-Dist: numpy (>=1.24.2,<2.0.0)
Requires-Dist: pytest (>=7.2.1,<8.0.0)
Requires-Dist: pytorch-lightning (>=2.0,<2.1)
Requires-Dist: pyyaml (>=6.0,<7.0)
Requires-Dist: rich (>=13.3.1,<14.0.0)
Requires-Dist: torch (>=2.0,<2.1)
Requires-Dist: torchvision
Requires-Dist: types-pyyaml (>=6.0.12.9,<7.0.0.0)
Project-URL: Documentation, https://candlefl.readthedocs.io/en/latest/
Project-URL: Issue Tracker, https://github.com/candlefl-org/candlefl/issues
Project-URL: Repository, https://github.com/candlefl-org/candlefl
